MANIFEST.in
README.txt
sc-releaser.cfg
setup.cfg
setup.py
collective/__init__.py
collective.ui.ie6nomore.egg-info/PKG-INFO
collective.ui.ie6nomore.egg-info/SOURCES.txt
collective.ui.ie6nomore.egg-info/dependency_links.txt
collective.ui.ie6nomore.egg-info/entry_points.txt
collective.ui.ie6nomore.egg-info/namespace_packages.txt
collective.ui.ie6nomore.egg-info/not-zip-safe
collective.ui.ie6nomore.egg-info/requires.txt
collective.ui.ie6nomore.egg-info/top_level.txt
collective/ui/__init__.py
collective/ui/ie6nomore/README.txt
collective/ui/ie6nomore/__init__.py
collective/ui/ie6nomore/configure.zcml
collective/ui/ie6nomore/profiles.zcml
collective/ui/ie6nomore/setuphandlers.py
collective/ui/ie6nomore/tests.py
collective/ui/ie6nomore/updateTranslations.sh
collective/ui/ie6nomore/version.txt
collective/ui/ie6nomore/browser/__init__.py
collective/ui/ie6nomore/browser/configure.zcml
collective/ui/ie6nomore/browser/interfaces.py
collective/ui/ie6nomore/browser/stylesheets/README.txt
collective/ui/ie6nomore/browser/templates/viewlet.pt
collective/ui/ie6nomore/doc/__init__.py
collective/ui/ie6nomore/doc/browser.txt
collective/ui/ie6nomore/locales/collective.ui.ie6nomore.manual.pot
collective/ui/ie6nomore/locales/collective.ui.ie6nomore.pot
collective/ui/ie6nomore/locales/empty.pt
collective/ui/ie6nomore/locales/pt_BR/LC_MESSAGES/collective.ui.ie6nomore.mo
collective/ui/ie6nomore/locales/pt_BR/LC_MESSAGES/collective.ui.ie6nomore.po
collective/ui/ie6nomore/profiles/default/collective.ie6nomore_various.txt
collective/ui/ie6nomore/profiles/default/import_steps.xml
collective/ui/ie6nomore/profiles/default/metadata.xml
collective/ui/ie6nomore/profiles/default/viewlets.xml
docs/HISTORY.txt
docs/INSTALL.txt
docs/LICENSE.GPL
docs/LICENSE.txt