Metadata-Version: 1.0
Name: collective.ui.ie6nomore
Version: 1.0
Summary: Enables a IE6 warning message instructing the user to download a newer (and better) browser.(Based on efforts initiated by http://www.ie6nomore.com/)
Home-page: http://www.simplesconsultoria.com.br/
Author: Simples Consultoria
Author-email: products@simplesconsultoria.com.br
License: GPL
Keywords: web zope plone theme skin plone3 ie ie6
Platform: UNKNOWN
Classifier: Framework :: Plone
Classifier: Framework :: Zope2
Classifier: Framework :: Zope3
Classifier: Programming Language :: Python
Classifier: Topic :: Software Development :: Libraries :: Python Modules
